LICENSE
README.md
nautobot_ui_plugin_docker/__init__.py
nautobot_ui_plugin_docker/admin.py
nautobot_ui_plugin_docker/api/__init__.py
nautobot_ui_plugin_docker/api/serializers.py
nautobot_ui_plugin_docker/api/urls.py
nautobot_ui_plugin_docker/api/views.py
nautobot_ui_plugin_docker/filters.py
nautobot_ui_plugin_docker/forms.py
nautobot_ui_plugin_docker/migrations/0001_initial.py
nautobot_ui_plugin_docker/migrations/__init__.py
nautobot_ui_plugin_docker/models.py
nautobot_ui_plugin_docker/navigation.py
nautobot_ui_plugin_docker/static/font-awesome-4.7.0/css/font-awesome.min.css
nautobot_ui_plugin_docker/static/nautobot_ui_plugin_docker/bootstrap.bundle.min.js
nautobot_ui_plugin_docker/static/nautobot_ui_plugin_docker/bootstrap.bundle.min.js.map
nautobot_ui_plugin_docker/static/nautobot_ui_plugin_docker/bootstrap.min.css
nautobot_ui_plugin_docker/static/nautobot_ui_plugin_docker/bootstrap.min.css.map
nautobot_ui_plugin_docker/static/nautobot_ui_plugin_docker/button_utils.js
nautobot_ui_plugin_docker/static/nautobot_ui_plugin_docker/img/dead_node.png
nautobot_ui_plugin_docker/static/nautobot_ui_plugin_docker/jquery/jquery-3.4.1.min.js
nautobot_ui_plugin_docker/static/nautobot_ui_plugin_docker/jquery/jquery-3.5.1.min.js
nautobot_ui_plugin_docker/static/nautobot_ui_plugin_docker/jquery/jquery-3.6.0.min.js
nautobot_ui_plugin_docker/static/nautobot_ui_plugin_docker/jquery-ui-1.12.1/jquery-ui.min.js
nautobot_ui_plugin_docker/static/nautobot_ui_plugin_docker/next_app.js
nautobot_ui_plugin_docker/static/nautobot_ui_plugin_docker/next_sources/LICENSE.txt
nautobot_ui_plugin_docker/static/nautobot_ui_plugin_docker/next_sources/css/next.css
nautobot_ui_plugin_docker/static/nautobot_ui_plugin_docker/next_sources/doc/api.js
nautobot_ui_plugin_docker/static/nautobot_ui_plugin_docker/next_sources/doc/assets/css/external-small.png
nautobot_ui_plugin_docker/static/nautobot_ui_plugin_docker/next_sources/doc/assets/css/logo.png
nautobot_ui_plugin_docker-0.10.16.dist-info/LICENSE
nautobot_ui_plugin_docker-0.10.16.dist-info/WHEEL
nautobot_ui_plugin_docker-0.10.16.dist-info/METADATA
nautobot_ui_plugin_docker-0.10.16.dist-info/RECORD
