Metadata-Version: 2.1
Name: nautobot-ui-plugin-docker
Version: 0.10.16
Summary: Nautobot UI Plugin
Home-page: https://github.com/ocalaf-unitenic/nautobot-ui-plugin-docker
License: Apache-2.0
Keywords: nautobot,nautobot-plugin
Author: Oscar Calaf
Author-email: ocalaf@unitecnic.com
Requires-Python: >=3.7,<4.0
Classifier: License :: OSI Approved :: Apache Software License
Classifier: Programming Language :: Python :: 3
Classifier: Programming Language :: Python :: 3.7
Classifier: Programming Language :: Python :: 3.8
Classifier: Programming Language :: Python :: 3.9
Classifier: Programming Language :: Python :: 3.10
Classifier: Programming Language :: Python :: 3.11
Requires-Dist: nautobot (>=1.2.0,<2.0.0)
Project-URL: Repository, https://gitlab-ce.gwdg.de/gwdg-netz/nautobot-plugins/nautobot-ui-plugin/
